shapecalc/Circle.py
shapecalc/Cone.py
shapecalc/Cube.py
shapecalc/Cuboid.py
shapecalc/Cylinder.py
shapecalc/Rectangle.py
shapecalc/Sector.py
shapecalc/Square.py
shapecalc/Triangle.py
shapecalc/__init__.py
shapecalc-1.0.2.dist-info/METADATA
shapecalc-1.0.2.dist-info/WHEEL
shapecalc-1.0.2.dist-info/top_level.txt
shapecalc-1.0.2.dist-info/RECORD
