Metadata-Version: 2.1
Name: shapecalc
Version: 1.0.2
Summary: A package for geometry calculation
Home-page: https://github.com/pypa/sampleproject
Author: Example Author
Author-email: authon@example.com
License: UNKNOWN
Project-URL: Bug Tracker, https://github.com/pypa/sampleproject/issues
Platform: UNKNOWN
Classifier: Programming Language :: Python :: 3
Classifier: License :: OSI Approved :: MIT License
Classifier: Operating System :: OS Independent
Requires-Python: >=3.6
